nvidia/nvimgcodec/include/nvimgcodec.h
nvidia/nvimgcodec/extensions/libnvpnm_ext.so.0.6.1
nvidia/nvimgcodec/extensions/libnvbmp_ext.so.0.6.1
nvidia/nvimgcodec/extensions/libjpeg_turbo_ext.so.0.6.1
nvidia/nvimgcodec/__init__.py
nvidia/__init__.py
nvidia_nvimgcodec_tegra_cu12-0.6.1.37.dist-info/WHEEL
nvidia/nvimgcodec/include/nvimgcodec_version.h
nvidia_nvimgcodec_tegra_cu12-0.6.1.37.dist-info/METADATA
nvidia/nvimgcodec/nvimgcodec_impl.cpython-310-aarch64-linux-gnu.so
nvidia_nvimgcodec_tegra_cu12-0.6.1.37.dist-info/top_level.txt
nvidia/nvimgcodec/extensions/libtiff_ext.so.0.6.1
nvidia/nvimgcodec/extensions/libnvjpeg2k_ext.so.0.6.1
nvidia/nvimgcodec/extensions/libnvtiff_ext.so.0.6.1
nvidia_nvimgcodec_tegra_cu12-0.6.1.37.dist-info/LICENSE.txt
nvidia/nvimgcodec/nvimgcodec_impl.cpython-313-aarch64-linux-gnu.so
nvidia/nvimgcodec/nvimgcodec_impl.cpython-39-aarch64-linux-gnu.so
nvidia/nvimgcodec/include/nvcv_adapter.hpp
nvidia/nvimgcodec/libnvimgcodec.so.0
nvidia/nvimgcodec/extensions/libopencv_ext.so.0.6.1
nvidia/nvimgcodec/extensions/libnvjpeg_ext.so.0.6.1
nvidia/nvimgcodec/nvimgcodec_impl.cpython-311-aarch64-linux-gnu.so
nvidia/nvimgcodec/nvimgcodec_impl.cpython-312-aarch64-linux-gnu.so
nvidia_nvimgcodec_tegra_cu12-0.6.1.37.dist-info/RECORD
